{
  "pmid": "42187594",
  "pmcid": "PMC13206130",
  "doi": "10.3390/curroncol33050277",
  "journal": "Current Oncology",
  "year": 2026,
  "title": "Docetaxel in Non-Small Cell Lung Cancer: A Multi-Centre Real-World Evidence Analysis in the Immunotherapy Era",
  "abstract": "AbstractDocetaxel has been a standard second-line or later (2L+) treatment for advanced non-small cell lung cancer (NSCLC) for more than two decades and remains recommended in current treatment algorithms. However, real-world outcomes in the era of immune checkpoint inhibitors (ICI) are limited. This multicenter retrospective study included patients with advanced NSCLC treated with 2L+ docetaxel monotherapy between January 2011 and December 2020. The primary endpoint was median overall survival (mOS) from docetaxel initiation. Subgroup analyses were conducted to identify predictors of OS. A total of 285 patients were analyzed. Median age was 62 years; 43% female, 75% ECOG performance status (PS) 0–1, and 65% adenocarcinoma. Molecular alterations included EGFR (20%) and KRAS (15%). PD-L1 status was available in 66% of patients. Median docetaxel exposure was three cycles, administered as 2L (48%), 3L (35%), or 4L+ (17%). Prior therapies included chemotherapy (96%), ICI (38%), targeted therapy (21%), and chemo-immunotherapy (10%). mOS was 6.5 months (95% CI, 5.9–7.3). On multivariate analysis, KRAS alteration (HR 0.59; 95% CI 0.37–0.94; p = 0.026) and ECOG PS (1 vs. 0 HR 2.26; 95% CI 1.15–4.43; p = 0.018, ≥2 vs. 0 HR 2.62; 95% CI 1.27–5.41; p = 0.0091) remained independent predictors of OS. Real-world OS with docetaxel is consistent with historical trial data, irrespective of prior ICI, targeted therapy, or chemo-immunotherapy. KRAS mutation and a favourable ECOG PS were associated with improved survival.",
  "discussion": "4. DiscussionIn this multicenter retrospective study, we report the real-world evidence (RWE) of palliative docetaxel monotherapy in the 2L+ setting in patients with advanced NSCLC upon progression after 1L chemotherapy, ICI, CIO, or targeted therapy. We also report on specific patient characteristics and predictors of response that affect mOS differences and hazard of death to 2L+ docetaxel therapy. Our findings suggest that docetaxel remains a clinically relevant option in the post-platinum setting, even in the era of targeted therapies and immune checkpoint inhibitors.The mOS of our overall cohort was 6.5 months (95% CI: 5.9–7.3 months), which is consistent with outcomes reported in pivotal trials such as TAX 317 (7.5 months) which helped establish docetaxel as the standard of care in 2L treatment of NSCLC . Previously reported 2L salvage docetaxel has been shown to have a mOS of 6.4–9.7, months which is consistent with our study . Our RWE mOS was on the lower end compared to previous studies. One explanation could be that in our study 25% of patients were ECOG PS ≥ 2, whereas several trials which reported the highest mOS did not include patients with ECOG PS ≥ 2 . This is standard for most clinical trials but does not fit with everyday patients in the clinic. Our mOS is consistent with the initial TAX study results, in which patients with ECOG performance status 2 comprised 24% of the trial population, comparable to the 25% observed in our cohort . Although the absolute survival benefit is modest, it is important to recognize the role of docetaxel in heavily pretreated patients, particularly those who have progressed on ICI, CIO, or targeted agents. Our data suggests that despite the addition of patients previously treated with immunotherapy (ICI mono/dual therapy, CIO) or targeted agents, overall treatment population mOS aligns with previous OS data in an era without immunotherapy. Our data continues to support the role of docetaxel use in the 2L+ setting in patients with metastatic NSCLC after progression, regardless of prior therapy.One of the earliest clinical trials examining docetaxel as any line agent after ICI in clinical practice was Tamura et al. who looked at docetaxel with or without ramucirumab after nivolumab . They reported better response to treatment post-ICI with improved ORR (27.8% vs. 16.0%). The group also reported that 2L taxane monotherapy had a mOS of 6.4 months (95% CI: 5.0–12.9) while taxane plus anti-angiogenic achieved the longest 2L mOS—not reached (95% CI: 5.8-NR). Previous studies have also shown a possible enhanced effect of 2L docetaxel post-progression on ICI with the addition of ramucirumab (8.6 vs. 19.8 months) but no difference without prior ICI therapy . In the United States, ramucirumab is a treatment option with 2L docetaxel, while in Canada this combination is not funded, with docetaxel being the most used treatment option after progression on ICI, CIO or targeted therapy.Our study population was reflective of routine clinical practice, with a heterogeneous mix of histologies, ECOG PS, total lines of therapy, line of docetaxel use and lines of therapy prior to docetaxel. A substantial proportion of patients received docetaxel as third-line or later, emphasizing its utility in salvage settings. Our driver mutation profile was similar to previous studies in Western populations with notably lower numbers of KRAS mutant tumours (15.4% in our study vs. 30–40%) and higher rates of EGFR mutations (20.4% in our study vs. 10–16%) in North American populations . A total of 103 (36.1%) patient tumours had not been evaluated for KRAS mutation due to a portion of our cohort existing in a time where KRAS testing was not the standard of care. Of the 182 who had their tumours evaluated, 28 were positive (15.4%). Despite this, our rates of KRAS mutation were lower than expected. Possibly explained by a subset of patients with SCC histology (27.4%), which are known to display lower rates of KRAS alterations compared to adenocarcinomas with most SCC histology not being evaluated based on standard of care practices in Ontario, Canada at that time. Only one patient with a SCC histology had a KRAS mutant tumour while of the adenocarcinoma patients who had available KRAS testing, 27/122 (22.1%) had a KRAS mutation. Slightly higher rates than expected of EGFR mutant tumours could be explained by a high proportion of patients treated with prior targeted therapy (78.7%) and never smokers (70.2%), selecting for fitter patients more likely to be treated with later lines of therapy. We also noted slightly higher rates of PD-L1 negative (<1%) at 54.5%. Although a recent global multicentre observational study reviewed real-world prevalence data and found that among 2435 patients 48.4% had a PD-L1 < 1% while 22.2% were PD-L1 high (≥50%), which was similar to our data at 19.6% . Variability in PD-L1 status has been shown be due to the specific assay clone used (22C3, 28-8, SP263), inter-laboratory variability, ethnic differences and tumour selection of prior therapy .Patient characteristics demonstrating predictive value in increasing mOS with 2L+ docetaxel included ECOG PS 0/1, duration since platinum therapy ≥ median duration since exposure to platinum use (4.6 months), absence of bony metastatic disease or patients with tumours possessing a KRAS mutation. Not surprisingly, patients who had a better functional status (ECOG PS 0/1) prior to the start of 2L+ docetaxel had improved OS. Conversely, having a higher ECOG PS of ≥2 was associated with a 141% increased hazard of death on univariate analysis and a sustained 162% increased hazard of death on multivariate analysis compared to patients with an ECOG PS 0 at time of docetaxel initiation. Duration since platinum therapy as a predictor is supported by previous studies where patients that progressed on 1L CIO who were considered responders (1L PFS ≥ 6 months) had improved OS compared to those who were considered resistant (PFS < 6 months) . This implies that patients who progressed within a shorter interval after discontinuing platinum-based therapy (<median time since treatment) had worse overall survival with docetaxel than those with a longer post-platinum treatment interval. The absence of bone metastasis improving mOS with palliative docetaxel is hypothesized in the literature with potential mechanisms including poor drug biodistribution in bone , bone microenvironment providing a sanctuary site via the CXCL12-CXCR4 axis and blunting of docetaxel efficacy with tumour–stroma signalling dependent on RANK/RANKL/OPG axis .Histology subtype also showed a predictive characteristic with large cell lung cancers displaying a 74% increased hazard of death compared to adenocarcinomas on univariate analysis. This is supported in the literature as large cell lung cancers have been consistently associated with a worse OS compared to adenocarcinoma; although, no previous studies have associated them with response to palliative docetaxel . It should be noted that the number of patients were low in the large cell histology (14; 4.9%) and, therefore, this predictive characteristic should be viewed more as hypothesis-generating and something for future studies to explore. Patients with duration of prior therapy ≤ 6 months had an increased hazard of death on univariate analysis (HR 1.4, p = 0.031) and a similar trend on multivariate analysis (HR 1.71, p = 0.072). These findings are consistent with prior literature which has shown that patients who were considered resistant to 1L treatment (progression < 6 months) or prior ICI-based treatment lasting ≥6 months had superior outcomes with OS and PFS . The only two patient characteristics which continued to display an association on multivariate analysis included ECOG PS 1 vs. 0/≥2 vs. 0 and tumours possessing a KRAS mutation with treatment of 2L+ docetaxel in metastatic NSCLC. This is consistent with prior literature demonstrating poorer outcomes with second-line docetaxel in patients with ECOG PS 2 compared with alternative chemotherapies such as pemetrexed . Based on these results, it would be reasonable to consider alternative treatment options or best supportive care for patients who have a poor ECOG PS (≥2) given the noted increased hazard of death with 2L+ docetaxel. Lastly, site-specific mOS demonstrates no significant differences across participating centres (Table 2). This suggests that inter-site variation in local treatment patterns, radiologic review, and imaging schedules did not materially influence endpoint assessment or introduce measurable centre-level confounding in this cohort.Longer mOS benefit and improved HR (47% reduction in the hazard of death) were shown in patients’ tumours that had a KRAS mutation. Possessing a KRAS mutation in metastatic NSCLC is thought to carry a worse OS compared to KRAS wild-type while the use of ICIs and PD-L1 status have been shown to increase OS with KRAS mutant tumours . In our study, analysis of all patients with KRAS mutant tumours revealed, 46% were treated with prior ICI while 29%, 14% and 11% were treated with prior chemotherapy, targeted therapy, or CIO, respectively. PD-L1 high (≥50%) was present in only 7% of these patients while 57% and 25% were PD-L1 1–49% and <1%, respectively. Therefore, the mOS benefit and decreased hazard of death can not be fully attributed in our patient population to prior treatment with ICI or PD-L1 high status. Further analysis of KRAS mutation subtypes showed a higher-than-expected proportion of G12A (46.4%) compared to lower rates in real-world databases (9–10%) and lower than expected G12C variants (25.0%) compared to previous studies (39–49%) . Although these differences were present, KRAS mutation subtype is not associated with survival difference in the current era of immunotherapy . Thus, despite our rates of KRAS subtype mutation being slightly different from large KRAS databases, we would not expect this increased rate of KRAS G12A to play a role on our protective effect noted with KRAS mutation status with 2L+ docetaxel therapy. Characteristics which displayed no predictive OS benefit or HR effect on survival with 2L+ docetaxel included prior therapy (chemo, ICI, CIO, targeted), palliative line of docetaxel, EGFR alterations, or other sites of metastasis aside from bone (contralateral lung, pleura, liver, brain). Exploratory analyses demonstrated no difference in ECOG performance status prior to docetaxel initiation between patients with and without prior ICI exposure, including median ECOG PS (one in both groups) and the proportion with ECOG PS ≥2, suggesting no baseline performance status imbalance between groups and further supporting our findings. The lack of impact on mOS of certain actionable genomic alterations should be viewed with caution and can not be used to draw any conclusions around predictive factors for response to 2L+ docetaxel due to the low number of patients with HER2 (n = 6; 3.5%), BRAF (n = 7; 3.9%), ROS1 (n = 4; 2.3%) and ALK (n = 3; 1.3%) alterations. These findings support a more nuanced patient selection for docetaxel therapy, although the retrospective design precludes definitive conclusions.Our response rates (ORR: 10.3%; DCR: 36.5%) were similar to previously published data. Previous studies of docetaxel in the 2L setting in NSCLC have noted ORR in the range of 8–21% and DCR in the range of 48–63% . One explanation for why our RWE data shows a lower end of response could be related to the overall lower ECOG PS used in these studies (ECOG PS 0–1) compared to our study cohort. The patient characteristic which displayed the greatest mOS benefit was investigator-assessed best response of a PR (17.2 months; 95% CI: 12.8–29.5; Figure 1), which was 1.7-fold higher than the next predictor of KRAS mutation. Highlighting the importance of clinician assessment during treatment, which we demonstrate can be closely associated with mOS benefit.As a real-world, retrospective analysis, this study is subject to several limitations, including potential selection bias and incomplete data capture. Heterogeneity in practice patterns across centres, variability in supportive care, and the absence of centralized radiologic review may have influenced outcomes. As three independent academic institutions were involved, no centralized molecular review was in place during the study period with molecular analysis conducted at local laboratories using site-specific validated assays. Consequently, there was variability in detection platforms, reagents, and interpretation criteria, particularly in the pre-NGS era. Because a portion of the study period occurred prior to 2015, when ICI/CIO use was largely restricted to clinical trial settings and monotherapy became standard practice subsequently, the observed proportion of patients with prior immunotherapy exposure may have been influenced. Incomplete molecular and PD-L1 data limited subgroup analyses. All patients in this study were treated at comprehensive cancer centres, which may limit the generalizability to community practice where patient populations and access to therapies and clinical trials may differ. Treatment-related adverse events were not captured, precluding assessment of toxicity and real-world management. Reason for docetaxel discontinuation or switch was not captured and thus limits assessment of real-world treatment patterns. Mortality data were derived solely from medical records without external linkage, potentially leading to survival overestimation, and cause-specific mortality could not be assessed. Despite these limitations, this study represents the first real-world evaluation of docetaxel monotherapy efficacy and predictors of response in a diverse, advanced NSCLC population treated in the 2L+ setting.Future studies should evaluate rational combination strategies to enhance docetaxel efficacy, including antiangiogenic agents and emerging immunomodulators, particularly in ICI-pretreated patients. As antibody–drug conjugates increasingly move into earlier lines of therapy, docetaxel may be further relegated to later-line settings, underscoring the need to better define patient characteristics associated with benefit. Incorporation of patient-reported outcomes will also be critical to contextualizing clinical benefit and quality of life in the refractory setting. As treatment paradigms evolve, clarifying the optimal role of docetaxel will remain essential to individualized care beyond immunotherapy.",
  "conclusion": "5. ConclusionsTo our knowledge, this is the largest multi-institute real-world study that has systematically investigated the patient characteristics and prognostic factors affecting OS with 2L+ docetaxel in patients treated with prior ICI, CIO, or targeted therapy. In this RWE study, docetaxel use in 2L+ setting showed similar mOS to initial clinical trials, regardless of prior ICI use. We show that prior use of palliative ICI, CIO or targeted therapy had no effect on OS with 2L+ docetaxel. Factors which were associated with prolonged OS with docetaxel as an independent predictor on multivariate analysis included presence of a KRAS mutation in tumours and a good ECOG PS (0/1) prior to docetaxel initiation. Our real-world data supports the overwhelming body of clinical trial evidence that continues to demonstrate a modest level of efficacy for single-agent docetaxel in the 2L+ setting. With the therapeutic landscape for advanced NSCLC evolving significantly with the advent of ICIs and targeted agents, we show there remains a critical need for effective cytotoxic options in patients who exhaust these modalities. Docetaxel, especially in monotherapy, continues to be a pragmatic and accessible option.",
  "figure_legends": [
    "Kaplan–Meier curve of OS based on 2L+ docetaxel response. PR—partial response, SD—stable disease, PD—progressive disease, DPRA—death prior to response assessment. Time reported in days since docetaxel start until death from any cause."
  ],
  "sections_available": {
    "abstract": true,
    "discussion": true,
    "conclusion": true,
    "figure_legends": true
  },
  "text_provenance": "pmc_jats",
  "journal_key": "pnas",
  "char_counts": {
    "abstract": 1527,
    "discussion": 14542,
    "conclusion": 1217,
    "figure_legends": 234
  }
}
