{
  "nlm_id": "8914574",
  "title": "Administration and policy in mental health",
  "abbreviation": "Adm Policy Ment Health",
  "issn": [
    "0894-587X",
    "1573-3289"
  ],
  "publisher": "Springer",
  "country": "United States",
  "submission_system": "Editorial Manager",
  "submission_url": "https://www.editorialmanager.com/",
  "detection_source": "publisher_map",
  "format_hints": {
    "word_format": "DOCX",
    "figures": "TIFF/EPS 300dpi+",
    "cover_letter": true
  },
  "schema_version": "2.0",
  "article_types": {
    "Article": {
      "max_words_main_text": 1500,
      "max_words_abstract": 250,
      "required_sections": [
        "Abstract",
        "Methods",
        "Results",
        "Acknowledgements",
        "Data Availability",
        "Author Contributions",
        "References",
        "Supplementary"
      ]
    }
  },
  "reference_style": "APA",
  "figure_format": [
    "TIFF (200 dpi min)"
  ],
  "figure_dpi": 200,
  "source_url": "https://link.springer.com/journal/10488/submission-guidelines#Instructions%20for%20Authors_Important%20Information%20on%20Manuscript%20Preparation%20and%20Submission"
}