{
  "nlm_id": "101220684",
  "title": "Archives of disease in childhood. Education and practice edition",
  "abbreviation": "Arch Dis Child Educ Pract Ed",
  "issn": [
    "1743-0585",
    "1743-0593"
  ],
  "publisher": "BMJ Pub. Group",
  "country": "England",
  "submission_system": "ScholarOne",
  "submission_url": "",
  "detection_source": "unknown",
  "format_hints": {
    "word_format": "check journal",
    "figures": "check journal",
    "cover_letter": null
  },
  "schema_version": "2.0"
}