{
  "nlm_id": "101648506",
  "title": "Health promotion and chronic disease prevention in Canada : research, policy and practice",
  "abbreviation": "Health Promot Chronic Dis Prev Can",
  "issn": [
    "2368-738X"
  ],
  "publisher": "Public Health Agency of Canada = Agence de la santé publique du Canada",
  "country": "Canada",
  "submission_system": "unknown",
  "submission_url": "",
  "detection_source": "unknown",
  "format_hints": {
    "word_format": "check journal",
    "figures": "check journal",
    "cover_letter": null
  },
  "schema_version": "2.0"
}