{
  "nlm_id": "101271023",
  "title": "Journal of perioperative practice",
  "abbreviation": "J Perioper Pract",
  "issn": [
    "1750-4589",
    "2515-7949"
  ],
  "publisher": "Sage in association with the Association for Perioperative Practice",
  "country": "England",
  "submission_system": "ScholarOne",
  "submission_url": "https://mc.manuscriptcentral.com/",
  "detection_source": "publisher_map",
  "format_hints": {
    "word_format": "DOCX or PDF",
    "figures": "TIFF/EPS 300dpi+",
    "cover_letter": true
  },
  "schema_version": "2.0"
}