{
  "nlm_id": "333507",
  "title": "Journal of youth and adolescence",
  "abbreviation": "J Youth Adolesc",
  "issn": [
    "0047-2891",
    "1573-6601"
  ],
  "publisher": "Kluwer Academic/Plenum Publishers",
  "country": "United States",
  "submission_system": "unknown",
  "submission_url": "",
  "detection_source": "unknown",
  "format_hints": {
    "word_format": "check journal",
    "figures": "check journal",
    "cover_letter": null
  },
  "schema_version": "1.0",
  "article_types": {
    "Article": {
      "max_words_main_text": 120,
      "max_words_abstract": 120,
      "required_sections": [
        "Abstract",
        "Introduction",
        "Results",
        "Discussion",
        "Acknowledgements",
        "Author Contributions",
        "References",
        "Supplementary"
      ]
    }
  },
  "reference_style": "APA",
  "figure_format": [
    "TIFF (200 dpi min)"
  ],
  "figure_dpi": 200,
  "source_url": "https://link.springer.com/journal/10964/submission-guidelines"
}