{
  "nlm_id": "9601804",
  "title": "Journal of mammary gland biology and neoplasia",
  "abbreviation": "J Mammary Gland Biol Neoplasia",
  "issn": [
    "1083-3021",
    "1573-7039"
  ],
  "publisher": "Kluwer Academic/Plenum Publishers",
  "country": "United States",
  "submission_system": "unknown",
  "submission_url": "",
  "detection_source": "unknown",
  "format_hints": {
    "word_format": "check journal",
    "figures": "check journal",
    "cover_letter": null
  },
  "schema_version": "1.0",
  "article_types": {
    "Article": {
      "max_words_main_text": 5000,
      "max_words_abstract": 750,
      "required_sections": [
        "Abstract",
        "Methods",
        "Results",
        "Discussion",
        "Acknowledgements",
        "Data Availability",
        "Author Contributions",
        "References",
        "Supplementary"
      ]
    }
  },
  "reference_style": "APA",
  "figure_format": [
    "TIFF (200 dpi min)"
  ],
  "figure_dpi": 200,
  "source_url": "https://link.springer.com/journal/10911/submission-guidelines"
}