{
  "nlm_id": "9700068",
  "title": "Journal of bodywork and movement therapies",
  "abbreviation": "J Bodyw Mov Ther",
  "issn": [
    "1360-8592",
    "1532-9283"
  ],
  "publisher": "Churchill Livingstone",
  "country": "United States",
  "submission_system": "Editorial Manager",
  "submission_url": "https://www.editorialmanager.com/",
  "detection_source": "crossref",
  "format_hints": {
    "word_format": "DOCX",
    "figures": "TIFF/EPS 300dpi+",
    "cover_letter": true
  },
  "schema_version": "2.0",
  "crossref_publisher": "Elsevier"
}