{
  "nlm_id": "9102705",
  "title": "Journal of neuroimaging : official journal of the American Society of Neuroimaging",
  "abbreviation": "J Neuroimaging",
  "issn": [
    "1051-2284",
    "1552-6569"
  ],
  "publisher": "Wiley",
  "country": "United States",
  "submission_system": "ScholarOne",
  "submission_url": "https://mc.manuscriptcentral.com/",
  "detection_source": "publisher_map",
  "format_hints": {
    "word_format": "DOCX or PDF",
    "figures": "TIFF/EPS 300dpi+",
    "cover_letter": true
  },
  "schema_version": "2.0"
}