{
  "nlm_id": "8109073",
  "title": "Medical decision making : an international journal of the Society for Medical Decision Making",
  "abbreviation": "Med Decis Making",
  "issn": [
    "0272-989X",
    "1552-681X"
  ],
  "publisher": "Sage Publications",
  "country": "United States",
  "submission_system": "ScholarOne",
  "submission_url": "https://mc.manuscriptcentral.com/",
  "detection_source": "publisher_map",
  "format_hints": {
    "word_format": "DOCX or PDF",
    "figures": "TIFF/EPS 300dpi+",
    "cover_letter": true
  },
  "schema_version": "2.0"
}