{
  "nlm_id": "9609063",
  "title": "Medical science monitor : international medical journal of experimental and clinical research",
  "abbreviation": "Med Sci Monit",
  "issn": [
    "1234-1010",
    "1643-3750"
  ],
  "publisher": "International Scientific Information, Inc.",
  "country": "United States",
  "submission_system": "ScholarOne",
  "submission_url": "https://mc.manuscriptcentral.com/",
  "detection_source": "publisher_map",
  "format_hints": {
    "word_format": "DOCX or PDF",
    "figures": "TIFF/EPS 300dpi+",
    "cover_letter": true
  },
  "schema_version": "2.0"
}