{
  "nlm_id": "101156086",
  "title": "Neurocritical care",
  "abbreviation": "Neurocrit Care",
  "issn": [
    "1541-6933",
    "1556-0961"
  ],
  "publisher": "Humana Press",
  "country": "United States",
  "submission_system": "Editorial Manager",
  "submission_url": "https://www.editorialmanager.com/",
  "detection_source": "crossref",
  "format_hints": {
    "word_format": "DOCX",
    "figures": "TIFF/EPS 300dpi+",
    "cover_letter": true
  },
  "schema_version": "2.0",
  "crossref_publisher": "Springer-Verlag"
}