{
  "display_name": "PLOS ONE",
  "issn": "1932-6203",
  "publisher": "PLOS",
  "submission_system": "Editorial Manager",
  "submission_url": "https://www.editorialmanager.com/pone/",
  "open_access_option": true,
  "open_access_apc_usd": 1749,
  "article_types": {
    "Research Article": {
      "max_words_main_text": null,
      "max_words_abstract": 300,
      "max_figures": null,
      "max_tables": null,
      "max_references": null,
      "required_sections": [
        "Abstract",
        "Introduction",
        "Materials and Methods",
        "Results",
        "Discussion"
      ],
      "notes": "No strict word or figure limits. Broader scope; technical soundness not novelty is key criterion."
    }
  },
  "reference_style": "AMA (numbered) or author-date",
  "figure_format": [
    "TIFF (300 dpi)",
    "EPS"
  ],
  "data_availability": "Required (data availability statement + deposit in public repository)",
  "preprint_policy": "Accepted",
  "impact_factor_approx": 2.9,
  "scope": "All scientific disciplines"
}