{
  "nlm_id": "101491319",
  "title": "PM & R : the journal of injury, function, and rehabilitation",
  "abbreviation": "PM R",
  "issn": [
    "1934-1482",
    "1934-1563"
  ],
  "publisher": "Wiley",
  "country": "United States",
  "submission_system": "ScholarOne",
  "submission_url": "https://mc.manuscriptcentral.com/",
  "detection_source": "publisher_map",
  "format_hints": {
    "word_format": "DOCX or PDF",
    "figures": "TIFF/EPS 300dpi+",
    "cover_letter": true
  },
  "schema_version": "2.0"
}