{
  "nlm_id": "7505876",
  "title": "Proceedings of the National Academy of Sciences of the United States of America",
  "abbreviation": "Proc Natl Acad Sci U S A",
  "issn": [
    "0027-8424",
    "1091-6490"
  ],
  "publisher": "National Academy of Sciences",
  "country": "United States",
  "submission_system": "PNAS Submit",
  "submission_url": "https://submit.pnas.org/",
  "detection_source": "title_override",
  "format_hints": {
    "word_format": "DOCX/LaTeX",
    "figures": "TIFF/EPS 600dpi",
    "cover_letter": true
  },
  "schema_version": "2.0"
}