{
  "nlm_id": "9704676",
  "title": "Techniques in hand & upper extremity surgery",
  "abbreviation": "Tech Hand Up Extrem Surg",
  "issn": [
    "1089-3393",
    "1531-6572"
  ],
  "publisher": "Lippincott Williams & Wilkins",
  "country": "United States",
  "submission_system": "Editorial Manager",
  "submission_url": "https://www.editorialmanager.com/",
  "detection_source": "publisher_map",
  "format_hints": {
    "word_format": "DOCX",
    "figures": "TIFF/EPS 300dpi+",
    "cover_letter": true
  },
  "schema_version": "1.0"
}